CHANGES.txt
MANIFEST.in
README.txt
setup.py
corejet/__init__.py
corejet.core.egg-info/PKG-INFO
corejet.core.egg-info/SOURCES.txt
corejet.core.egg-info/dependency_links.txt
corejet.core.egg-info/entry_points.txt
corejet.core.egg-info/namespace_packages.txt
corejet.core.egg-info/not-zip-safe
corejet.core.egg-info/requires.txt
corejet.core.egg-info/top_level.txt
corejet/core/__init__.py
corejet/core/decorators.py
corejet/core/interfaces.py
corejet/core/model.py
corejet/core/parser.py
corejet/core/testcase.py
corejet/core/locales/gherkin.pot
corejet/core/locales/en/LC_MESSAGES/gherkin.mo
corejet/core/locales/en/LC_MESSAGES/gherkin.po
corejet/core/locales/fi/LC_MESSAGES/gherkin.mo
corejet/core/locales/fi/LC_MESSAGES/gherkin.po
corejet/core/scripts/__init__.py
corejet/core/scripts/corejet2py.py
corejet/core/tests/__init__.py
corejet/core/tests/test_backround.py
corejet/core/tests/test_but.py
corejet/core/tests/test_fi.py
corejet/core/tests/test_outline.py
corejet/core/tests/test_parse.py
corejet/core/tests/test_serialize.py
corejet/core/xslt/corejet-to-python.xsl