Metadata-Version: 1.1
Name: corejet.core
Version: 1.1.0
Summary: Defines test infrastructure for building CoreJet tests
Home-page: http://corejet.org
Author: Martin Aspeli
Author-email: optilude@gmail.com
License: ZPL 2.1
Keywords: corejet zope.testing
Platform: UNKNOWN
Classifier: Programming Language :: Python
